ds4n6_chrysalis/__init__.py
ds4n6_chrysalis/amcache.py
ds4n6_chrysalis/autoruns.py
ds4n6_chrysalis/common.py
ds4n6_chrysalis/d4.py
ds4n6_chrysalis/evtx.py
ds4n6_chrysalis/evtx_parser.py
ds4n6_chrysalis/flist.py
ds4n6_chrysalis/fstl.py
ds4n6_chrysalis/gui.py
ds4n6_chrysalis/kansa.py
ds4n6_chrysalis/kape.py
ds4n6_chrysalis/knowledge.py
ds4n6_chrysalis/macrobber.py
ds4n6_chrysalis/mactime.py
ds4n6_chrysalis/ml.py
ds4n6_chrysalis/pf.py
ds4n6_chrysalis/plaso.py
ds4n6_chrysalis/pslist.py
ds4n6_chrysalis/sabonis.py
ds4n6_chrysalis/svclist.py
ds4n6_chrysalis/tshark.py
ds4n6_chrysalis/unx.py
ds4n6_chrysalis/utils.py
ds4n6_chrysalis/volatility.py
ds4n6_chrysalis/winreg.py
ds4n6_chrysalis-0.7.2.dist-info/LICENSE
ds4n6_chrysalis-0.7.2.dist-info/METADATA
ds4n6_chrysalis-0.7.2.dist-info/WHEEL
ds4n6_chrysalis-0.7.2.dist-info/top_level.txt
ds4n6_chrysalis-0.7.2.dist-info/RECORD
