Metadata-Version: 2.1
Name: ds4n6-chrysalis
Version: 0.7.2
Summary: Bringing Data Science & Artificial Intelligence to the fingertips of the average Forensicator, and promote advances in the field
Home-page: https://github.com/ds4n6/ds4n6_chrysalis
Author: Jess Garcia
Author-email: ds4n6@one-esecurity.com
Project-URL: Bug Tracker, https://github.com/ds4n6/ds4n6_chrysalis/issues
Project-URL: Website, http://www.ds4n6.io/
Keywords: dfir,datascience,forensics
Classifier: Development Status :: 3 - Alpha
Classifier: Intended Audience :: Developers
Classifier: Intended Audience :: Information Technology
Classifier: Framework :: Jupyter
Classifier: Topic :: Security
Classifier: Topic :: Scientific/Engineering :: Artificial Intelligence
Classifier: Topic :: Software Development :: Libraries :: Python Modules
Classifier: Programming Language :: Python :: 3
Classifier: License :: OSI Approved :: GNU General Public License v3 (GPLv3)
Classifier: Operating System :: OS Independent
Requires-Python: >=3.6
License-File: LICENSE
Requires-Dist: requests
Requires-Dist: numpy
Requires-Dist: pandas
Requires-Dist: Evtx
Requires-Dist: python-evtx
Requires-Dist: ipyaggrid
Requires-Dist: IPython
Requires-Dist: ipywidgets
Requires-Dist: keras
Requires-Dist: matplotlib
Requires-Dist: nbformat
Requires-Dist: pyparsing
Requires-Dist: qgrid
Requires-Dist: ruamel.yaml
Requires-Dist: sklearn
Requires-Dist: tensorflow
Requires-Dist: tqdm
Requires-Dist: traitlets
Requires-Dist: xmltodict
